gpz/__init__.py
gpz/abc.py
gpz/gp.py
gpz/util.py
gpz/kernels/__init__.py
gpz/kernels/constant.py
gpz/kernels/exponential.py
gpz/kernels/gaussian.py
gpz/kernels/matern.py
gpz/kernels/stationary.py
gpz/means/__init__.py
gpz/means/additive.py
gpz/means/constant.py
gpz/means/polynomial.py
gpz/selection/__init__.py
gpz/selection/abc.py
gpz/selection/lik.py
gpz/selection/loo.py
gpz/selection/mixins.py
gpz-1.0.0.dist-info/LICENSE
gpz-1.0.0.dist-info/METADATA
gpz-1.0.0.dist-info/WHEEL
gpz-1.0.0.dist-info/top_level.txt
gpz-1.0.0.dist-info/RECORD
