Metadata-Version: 2.1
Name: gpz
Version: 1.0.0
Summary: Gaussian process regression.
Home-page: UNKNOWN
Author: Paul FELIOT
Author-email: p.feliot@hotmail.fr
License: UNKNOWN
Platform: UNKNOWN
Requires-Python: >=3.6
License-File: LICENSE
Requires-Dist: numpy
Requires-Dist: scipy
